pulumi_cloudru/__init__.py
pulumi_cloudru/_inputs.py
pulumi_cloudru/_utilities.py
pulumi_cloudru/apig_acl_policy.py
pulumi_cloudru/apig_acl_policy_associate.py
pulumi_cloudru/apig_api_action.py
pulumi_cloudru/apig_api_batch_action.py
pulumi_cloudru/apig_api_check.py
pulumi_cloudru/apig_api_debug.py
pulumi_cloudru/apig_api_version_unpublish.py
pulumi_cloudru/apig_appcode.py
pulumi_cloudru/apig_application_acl.py
pulumi_cloudru/apig_application_authorization.py
pulumi_cloudru/apig_application_quota.py
pulumi_cloudru/apig_application_quota_associate.py
pulumi_cloudru/apig_certificate.py
pulumi_cloudru/apig_channel.py
pulumi_cloudru/apig_endpoint_connection_management.py
pulumi_cloudru/apig_endpoint_whitelist.py
pulumi_cloudru/apig_environment_variable.py
pulumi_cloudru/apig_instance_feature.py
pulumi_cloudru/apig_instance_routes.py
pulumi_cloudru/apig_plugin.py
pulumi_cloudru/apig_plugin_associate.py
pulumi_cloudru/apig_plugin_batch_apis_associate.py
pulumi_cloudru/apig_signature.py
pulumi_cloudru/apig_signature_associate.py
pulumi_cloudru/cbh_asset_agency_authorization.py
pulumi_cloudru/cbh_ha_instance.py
pulumi_cloudru/cbh_instance.py
pulumi_cloudru/cbr_backup_share.py
pulumi_cloudru/cbr_backup_share_accepter.py
pulumi_cloudru/cbr_checkpoint.py
pulumi_cloudru/cce_cluster_upgrade.py
pulumi_cloudru/cce_nodes_remove.py
pulumi_cloudru/css_configuration.py
pulumi_cloudru/dcs_account.py
pulumi_cloudru/dcs_backup.py
pulumi_cloudru/dcs_parameters.py
pulumi_cloudru/dcs_restore.py
pulumi_cloudru/dds_parameter_template.py
pulumi_cloudru/dds_parameter_template_apply.py
pulumi_cloudru/dds_parameter_template_compare.py
pulumi_cloudru/dds_parameter_template_copy.py
pulumi_cloudru/dds_parameter_template_reset.py
pulumi_cloudru/dms_instance.py
pulumi_cloudru/dms_kafka_consumer_group.py
pulumi_cloudru/dms_kafka_message_produce.py
pulumi_cloudru/dms_rocketmq_consumer_group.py
pulumi_cloudru/dms_rocketmq_consumption_verify.py
pulumi_cloudru/dms_rocketmq_dead_letter_resend.py
pulumi_cloudru-1.0.0a1760458278.dist-info/METADATA
pulumi_cloudru-1.0.0a1760458278.dist-info/WHEEL
pulumi_cloudru-1.0.0a1760458278.dist-info/top_level.txt
pulumi_cloudru-1.0.0a1760458278.dist-info/RECORD
