Metadata-Version: 2.4
Name: pulumi_cloudru
Version: 1.0.0a1760458278
Summary: A Pulumi package for creating and managing cloud.ru cloud resources.
License: Apache-2.0
Project-URL: Homepage, https://cloud.ru/advanced
Project-URL: Repository, https://github.com/sbercloud-terraform/pulumi-cloudru
Keywords: cloudru,cloud,cloud.ru,cloud-ru,sbercloud,category/cloud
Requires-Python: >=3.9
Requires-Dist: parver>=0.2.1
Requires-Dist: pulumi<4.0.0,>=3.165.0
Requires-Dist: semver>=2.8.1
Requires-Dist: typing-extensions<5,>=4.11; python_version < "3.11"
